exsite/__init__.py
exsite/core.py
exsite/design.py
exsite/form.py
exsite/html.py
exsite/js.py
exsite/navbar.py
exsite/project.py
exsite/router.py
exsite/setup.py
exsite/template.py
exsite-1.1.0.dist-info/licenses/LICENSE
exsite-1.1.0.dist-info/METADATA
exsite-1.1.0.dist-info/WHEEL
exsite-1.1.0.dist-info/top_level.txt
exsite-1.1.0.dist-info/RECORD
