Metadata-Version: 2.4
Name: exsite
Version: 1.1.0
Summary: EXSITE – ابزار ساخت سایت و اپ HTML با طراحی مدرن
Home-page: https://github.com/EXLTeam/exsite
Author: EXL Team
Author-email: exl.dev.team@gmail.com
License: MIT
Keywords: html builder,css generator,website builder,python web tool,exsite
Classifier: Development Status :: 4 - Beta
Classifier: Intended Audience :: Developers
Classifier: Programming Language :: Python :: 3
Classifier: Operating System :: OS Independent
Classifier: License :: OSI Approved :: MIT License
Classifier: Topic :: Software Development :: Code Generators
Classifier: Topic :: Internet :: WWW/HTTP :: Site Management
Requires-Python: >=3.6
License-File: LICENSE
Dynamic: author
Dynamic: author-email
Dynamic: classifier
Dynamic: description
Dynamic: description-content-type
Dynamic: home-page
Dynamic: keywords
Dynamic: license
Dynamic: license-file
Dynamic: requires-python
Dynamic: summary
